fast_statistics-0.2.0.dist-info/RECORD
fast_statistics-0.2.0.dist-info/WHEEL
fast_statistics-0.2.0.dist-info/LICENSE
fast_statistics-0.2.0.dist-info/METADATA
fast_statistics-0.2.0.dist-info/top_level.txt
fast_stat/fast_stat.cpython-35m-x86_64-linux-gnu.so
fast_stat/fast_stat.cpython-36m-x86_64-linux-gnu.so
fast_stat/fast_stat.cpython-37m-x86_64-linux-gnu.so
fast_stat/__init__.py
