Metadata-Version: 2.1
Name: fast-statistics
Version: 0.2.0
Summary: Rust extension intended to be a faster version of built-in python statistics package
Home-page: https://github.com/risboo6909/fast-statistics
Author: Boris Tatarintsev
Author-email: UNKNOWN
License: UNKNOWN
Platform: UNKNOWN
Classifier: License :: OSI Approved :: MIT License
Classifier: Development Status :: 3 - Alpha
Classifier: Intended Audience :: Developers
Classifier: Programming Language :: Python :: 3.5
Classifier: Programming Language :: Python :: 3.6
Classifier: Programming Language :: Python :: 3.7
Classifier: Programming Language :: Rust
Classifier: Operating System :: POSIX
